AUTHORS
INSTALL
LICENSE
MANIFEST.in
README.rst
setup.py
django_rstamper.egg-info/PKG-INFO
django_rstamper.egg-info/SOURCES.txt
django_rstamper.egg-info/dependency_links.txt
django_rstamper.egg-info/not-zip-safe
django_rstamper.egg-info/requires.txt
django_rstamper.egg-info/top_level.txt
docs/Makefile
docs/source/conf.py
docs/source/index.rst
rstamper/__init__.py
rstamper/admin.py
rstamper/models.py
rstamper/rtimes.py
rstamper/tests.py
rstamper/urls.py
rstamper/views.py
rstamper/management/__init__.py
rstamper/management/commands/__init__.py
rstamper/management/commands/export.py
rstamper/management/commands/import.py
rstamper/migrations/0001_initial.py
rstamper/migrations/0002_auto__add_unique_customer_name.py
rstamper/migrations/0003_auto__chg_field_stamp_action.py
rstamper/migrations/0004_auto__chg_field_stamp_end.py
rstamper/migrations/0005_auto__chg_field_stamp_action.py
rstamper/migrations/__init__.py
rstamper/templates/rstamper/photos.html
rstamper/templates/rstamper/videos.html